yahoo_historical/__init__.py
yahoo_historical/constants.py
yahoo_historical/fetch.py
yahoo_historical-1.0.0.dist-info/LICENSE.txt
yahoo_historical-1.0.0.dist-info/METADATA
yahoo_historical-1.0.0.dist-info/WHEEL
yahoo_historical-1.0.0.dist-info/top_level.txt
yahoo_historical-1.0.0.dist-info/RECORD
