Metadata-Version: 2.1
Name: yahoo-historical
Version: 1.0.0
Summary: Fetches historical EOD (end of day) prices from yahoo finance
Home-page: https://github.com/AndrewRPorter/yahoo-historical
Download-URL: https://github.com/AndrewRPorter/yahoo-historical/releases
Author: Andrew Porter
Author-email: porter.r.andrew@gmail.com
License: MIT License
License-File: LICENSE.txt
Requires-Dist: setuptools
Requires-Dist: pandas
Requires-Dist: requests
